[
{
"UserType":"Maker",
"UserName":"1002435",
"PassWord":"admin",
"UserNameUAT":"1002435",
"PassWordUAT":"admin"
},
{
"UserType":"Reviewer",
"UserName":"12345",
"PassWord":"Admin@@11",
"UserName1":"1002436",
"PassWord1":"admin",
"UserName2":"1993",
"PassWord2":"Admin@@11",
"UserName3" : "in00027",
"PassWord3":"admin",
"UserName4" : "1002439",
"PassWord4":"Admin@1",
"UserName5" : "le4checker",
"PassWord5":"Admin@1"

},
{
"UserType":"Checker",
"UserName":"1002437",
"PassWord":"Admin@1"
}

]

