[
	{
		"usertType": "Maker",
		"warningPecentage": "28",
		"remark": "Ok",
		"uatYearlyBudgetCode": "BUDG019011",
		"uatMonthlyBudgetCode": "BUDG019012",
		"uatHalfYearlyBudgetCode": "BUDG019013",
		"uatQuarterlyBudgetCode": "BUDG019014",
		"uatCurrentFinancialBudgetCode":"BUDG0502",
		"uatYearlyBudgetType": "Capital Budgets",
		"uatMonthlyBudgetType": "Financial Plan",
		"uatHalfYearlyBudgetType": "Departments",
		"uatQuarterlyBudgetType": "Revenue Budget",
		"approvalCommentsFromReviewer": "Approved from Reviewer",
		"approvalCommentsFromChecker": "Approved from Checker",
		
		
		
		
		//Budget Transfer Report
		"Month":"Oct",
	"FullMonth":"October",
	"Year":"2022",
	"Day":"31"
	}
]
